azure/__init__.py
azure_nspkg-3.0.1.dist-info/DESCRIPTION.rst
azure_nspkg-3.0.1.dist-info/METADATA
azure_nspkg-3.0.1.dist-info/RECORD
azure_nspkg-3.0.1.dist-info/WHEEL
azure_nspkg-3.0.1.dist-info/metadata.json
azure_nspkg-3.0.1.dist-info/top_level.txt
